<mvc:View xmlns:mvc="sap.ui.core.mvc" xmlns="sap.m" controllerName="exercise1.controller.MainView">
    <Page id="page" title="{i18n>title}">
    <content>
    <sap.ui.layout.form:Form xmlns:sap.ui.layout.form="sap.ui.layout.form" editable="true" id="form0">
    <sap.ui.layout.form:formContainers>
    <sap.ui.layout.form:FormContainer title="Exercise 1" id="container0">
        <sap.ui.layout.form:formElements>
        <sap.ui.layout.form:FormElement label="Name" id="element0">
        <sap.ui.layout.form:fields>
        <Input width="100%" id="name_field" maxLength="35"/>

        </sap.ui.layout.form:fields>
        </sap.ui.layout.form:FormElement>

        <sap.ui.layout.form:FormElement label="Street/No" id="element0_1747731045483">
        <sap.ui.layout.form:fields>
        <Input width="100%" id="streetno1" maxLength="35"/>
        <Input width="100%" id="streetno2" maxLength="5"/>

        </sap.ui.layout.form:fields>
        </sap.ui.layout.form:FormElement>

        <sap.ui.layout.form:FormElement label="Zip Code/City" id="element1">
        <sap.ui.layout.form:fields>
        <Input width="100%" id="zipcocit1" maxLength="5"/>
        <Input width="100%" id="zipcocit2" maxLength="35"/>

        </sap.ui.layout.form:fields>
        </sap.ui.layout.form:FormElement>

        <sap.ui.layout.form:FormElement label="Country" id="element0_1747732943979">
        <sap.ui.layout.form:fields>
        <ComboBox xmlns="sap.m" id="countryfield" maxWidth="7100%">
        <items>
        <core:Item xmlns:core="sap.ui.core" key="item-1-key" text="England" id="item1"/>
            <core:Item xmlns:core="sap.ui.core" key="item-2-key" text="Germany" id="item2"/>
            <core:Item xmlns:core="sap.ui.core" key="item-3-key" text="USA" id="item3"/>
            <core:Item xmlns:core="sap.ui.core" key="item-4-key" text="Philippines" id="item4"/>
            </items>
        </ComboBox>
        </sap.ui.layout.form:fields>
        </sap.ui.layout.form:FormElement>
        </sap.ui.layout.form:formElements>

        </sap.ui.layout.form:FormContainer>
        </sap.ui.layout.form:formContainers>
    <sap.ui.layout.form:layout>
    <sap.ui.layout.form:ResponsiveGridLayout id="layout0"/>
    </sap.ui.layout.form:layout></sap.ui.layout.form:Form><Button xmlns="sap.m" text="Save" id="save_butt" type="Accept"/>
        <Button xmlns="sap.m" text="Clear" id="clear_butt" type="Transparent" press="onClear"/>
    </content>
    </Page>
</mvc:View>